[
    {
    "icon": "",
    "title": "Mother6",
    "description": "Page description",
    "imageCover": "https://picsum.photos/seed/our!mother6/960/640",
    "imagePreview": "https://picsum.photos/seed/our!mother6/640/560",
    "imagePreviewMini": "https://picsum.photos/seed/our!mother6/320/240",
    "date": "2022-07-08 06:39",
    "link": "/pages/our/mother6/"
    },
    {
    "icon": "",
    "title": "Mother5",
    "description": "Page description",
    "imageCover": "https://picsum.photos/seed/our!mother5/960/640",
    "imagePreview": "https://picsum.photos/seed/our!mother5/640/560",
    "imagePreviewMini": "https://picsum.photos/seed/our!mother5/320/240",
    "date": "2022-07-08 06:29",
    "link": "/pages/our/mother5/"
    },
    {
    "icon": "",
    "title": "Mother4",
    "description": "Page description",
    "imageCover": "https://picsum.photos/seed/our!mother4/960/640",
    "imagePreview": "https://picsum.photos/seed/our!mother4/640/560",
    "imagePreviewMini": "https://picsum.photos/seed/our!mother4/320/240",
    "date": "2022-07-08 06:27",
    "link": "/pages/our/mother4/"
    },
    {
    "icon": "",
    "title": "Mother3",
    "description": "Page description",
    "imageCover": "https://picsum.photos/seed/our!mother3/960/640",
    "imagePreview": "https://picsum.photos/seed/our!mother3/640/560",
    "imagePreviewMini": "https://picsum.photos/seed/our!mother3/320/240",
    "date": "2022-07-08 06:27",
    "link": "/pages/our/mother3/"
    },
    {
    "icon": "",
    "title": "Mother2",
    "description": "Page description",
    "imageCover": "https://picsum.photos/seed/our!mother2/960/640",
    "imagePreview": "https://picsum.photos/seed/our!mother2/640/560",
    "imagePreviewMini": "https://picsum.photos/seed/our!mother2/320/240",
    "date": "2022-07-08 06:22",
    "link": "/pages/our/mother2/"
    },
    {
    "icon": "",
    "title": "Mother1",
    "description": "Page description",
    "imageCover": "https://picsum.photos/seed/our!mother1/960/640",
    "imagePreview": "https://picsum.photos/seed/our!mother1/640/560",
    "imagePreviewMini": "https://picsum.photos/seed/our!mother1/320/240",
    "date": "2022-07-08 06:19",
    "link": "/pages/our/mother1/"
    }
]

